ssm_connect/__init__.py
ssm_connect/__main__.py
ssm_connect/gateway.py
ssm_connect/inventory.py
ssm_connect/main.py
ssm_connect-1.5.1.dist-info/licenses/LICENSE
ssm_connect-1.5.1.dist-info/METADATA
ssm_connect-1.5.1.dist-info/WHEEL
ssm_connect-1.5.1.dist-info/entry_points.txt
ssm_connect-1.5.1.dist-info/top_level.txt
ssm_connect-1.5.1.dist-info/RECORD
