Metadata-Version: 2.4
Name: ssm-connect
Version: 1.5.1
Summary: Interactive CLI to connect to AWS EC2 and RDS via SSM or SSH-over-SSM, with credential persistence and multi-session support.
Author-email: Siby Jose <jose.siby@icloud.com>
License: Apache-2.0
Project-URL: Homepage, https://github.com/JoseSiby/ssm-connect
Project-URL: Issues, https://github.com/JoseSiby/ssm-connect/issues
Project-URL: Source, https://github.com/JoseSiby/ssm-connect
Project-URL: Changelog, https://github.com/JoseSiby/ssm-connect/blob/main/CHANGELOG.md
Keywords: aws,ec2,rds,ssm,ssh,cli,session-manager,devops,cloud,sre,operations,infrastructure,port-forwarding,bastion,systems-manager,amazon-web-services,aws-ssm,remote-access,tunneling
Classifier: Development Status :: 5 - Production/Stable
Classifier: Intended Audience :: Developers
Classifier: Intended Audience :: System Administrators
Classifier: Environment :: Console
Classifier: Operating System :: OS Independent
Classifier: Programming Language :: Python :: 3
Classifier: Programming Language :: Python :: 3 :: Only
Classifier: Programming Language :: Python :: 3.8
Classifier: Programming Language :: Python :: 3.9
Classifier: Programming Language :: Python :: 3.10
Classifier: Programming Language :: Python :: 3.11
Classifier: Programming Language :: Python :: 3.12
Classifier: Programming Language :: Python :: 3.13
Classifier: Topic :: System :: Systems Administration
Classifier: Topic :: Utilities
Classifier: License :: OSI Approved :: Apache Software License
Requires-Python: >=3.8
License-File: LICENSE
Requires-Dist: boto3>=1.26.0
Dynamic: license-file
